dynamodb_python_lib/__init__.py
dynamodb_python_lib/proxy.py
dynamodb_python_lib/utility.py
dynamodb_python_lib/utilities/__init__.py
dynamodb_python_lib/utilities/annotating_data.py
dynamodb_python_lib/utilities/cleaning_data.py
dynamodb_python_lib/utilities/scoring_data.py
dynamodb_python_lib/utilities/synonym_map.py
dynamodb_python_lib/utilities/tagging_level_1_ner.py
dynamodb_python_lib-0.0.2.dist-info/METADATA
dynamodb_python_lib-0.0.2.dist-info/WHEEL
dynamodb_python_lib-0.0.2.dist-info/top_level.txt
dynamodb_python_lib-0.0.2.dist-info/RECORD
