Metadata-Version: 2.1
Name: dynamodb-python-lib
Version: 0.0.2
Summary: Brokers access to CP NLU data in DynamoDB.
Home-page: https://github.expedia.biz/ECP/dynamodb-python-lib
Author: DI Matrix
Author-email: DCIMatrix@expedia.com
License: UNKNOWN
Platform: UNKNOWN
Requires-Python: >=3.6
Requires-Dist: python-dateutil (==2.8.0)
Requires-Dist: boto3 (==1.11.14)
Requires-Dist: pandas (==0.25.3)
Requires-Dist: requests (==2.22.0)
Requires-Dist: language-check (==1.1)
Requires-Dist: gingerit (==0.8.0)
Requires-Dist: textblob (==0.15.3)
